kort_client/__init__.py
kort_client/api.py
kort_client/card_detectors.py
kort_client/cli.py
kort_client/config.py
kort_client/run.py
kort_client/usb_barcode_scanner/__init__.py
kort_client/usb_barcode_scanner/scanner.py
kort_client-0.1.1.dist-info/METADATA
kort_client-0.1.1.dist-info/WHEEL
kort_client-0.1.1.dist-info/entry_points.txt
kort_client-0.1.1.dist-info/RECORD
