Metadata-Version: 2.1
Name: kort-client
Version: 0.1.1
Summary: 
Author: Jonathan Weth
Author-email: git@jonathanweth.de
Requires-Python: >=3.9,<4.0
Classifier: Programming Language :: Python :: 3
Classifier: Programming Language :: Python :: 3.9
Classifier: Programming Language :: Python :: 3.10
Classifier: Programming Language :: Python :: 3.11
Requires-Dist: click (>=8.0.4,<9.0.0)
Requires-Dist: nfcpy (>=1.0.4,<2.0.0)
Requires-Dist: pycups (>=2.0.1,<3.0.0)
Requires-Dist: requests (>=2.27.1,<3.0.0)
Requires-Dist: usb-barcode-scanner-julz (>=0.2,<0.3)
Requires-Dist: usersettings (>=1.1.5,<2.0.0)
